avaml/__init__.py
avaml/prepare.py
avaml-0.0.6.dist-info/LICENSE
avaml-0.0.6.dist-info/METADATA
avaml-0.0.6.dist-info/WHEEL
avaml-0.0.6.dist-info/top_level.txt
avaml-0.0.6.dist-info/RECORD
