Metadata-Version: 2.1
Name: avaml
Version: 0.0.6
Summary: Facilitating machine learning in the Norwegian Avalanche Forecasting Service
Home-page: https://github.com/NVE/avaml
Author: Aron Widforss
Author-email: arwi@nve.no
License: UNKNOWN
Platform: UNKNOWN
Classifier: Programming Language :: Python :: 3
Classifier: License :: OSI Approved :: MIT License
Classifier: Operating System :: OS Independent
Requires-Python: >=3.6
License-File: LICENSE
Requires-Dist: pandas
Requires-Dist: numpy
Requires-Dist: regobslib (>=0.2.4)
Requires-Dist: setuptools
